definit_db_py/__init__.py
definit_db_py/config.py
definit_db_py/generate_db_md.py
definit_db_py/data_md/field/computer_science/index.md
definit_db_py/data_md/field/computer_science/definitions/algorithms/problems/hash_collision.md
definit_db_py/data_md/field/computer_science/definitions/algorithms/problems/rolling_hash.md
definit_db_py/data_md/field/computer_science/definitions/algorithms/problems/graph_labeling/graph_coloring.md
definit_db_py/data_md/field/computer_science/definitions/algorithms/problems/graph_labeling/graph_labeling.md
definit_db_py/data_md/field/computer_science/definitions/algorithms/problems/graph_labeling/vertex_coloring.md
definit_db_py/data_md/field/computer_science/definitions/algorithms/problems/property/overlapping_subproblems.md
definit_db_py/data_md/field/computer_science/definitions/algorithms/searching/string/rabin_karp_algorithm.md
definit_db_py/data_md/field/computer_science/definitions/data_structure/abstract_data_type.md
definit_db_py/data_md/field/computer_science/definitions/data_structure/bit_field.md
definit_db_py/data_md/field/computer_science/definitions/data_structure/map.md
definit_db_py/data_md/field/computer_science/definitions/data_structure/primitive_data_type.md
definit_db_py/data_md/field/computer_science/definitions/data_structure/collection/associative_array.md
definit_db_py/data_md/field/computer_science/definitions/data_structure/collection/bag.md
definit_db_py/data_md/field/computer_science/definitions/data_structure/collection/collection.md
definit_db_py/data_md/field/computer_science/definitions/data_structure/collection/hash_table.md
definit_db_py/data_md/field/computer_science/definitions/data_structure/collection/heap_tree.md
definit_db_py/data_md/field/computer_science/definitions/data_structure/collection/priority_queue.md
definit_db_py/data_md/field/computer_science/definitions/data_structure/collection/queue.md
definit_db_py/data_md/field/computer_science/definitions/data_structure/collection/set.md
definit_db_py-0.1.7.dist-info/METADATA
definit_db_py-0.1.7.dist-info/WHEEL
definit_db_py-0.1.7.dist-info/top_level.txt
definit_db_py-0.1.7.dist-info/RECORD
