Metadata-Version: 2.4
Name: definit-db-py
Version: 0.1.7
Summary: DefinIT database
Requires-Python: >=3.12
